[
  {
    "FOLIO": "37",
    "RESULTADO_AUDITORIA": "FALTA: FINAL",
    "CALLE": "Jose Maria Gonzalez Arratia",
    "COLONIA": "Santa Clara",
    "DELEGACION": "CENTRO HISTÓRICO",
    "_company": "ROCADURA",
    "_stage": "E2"
  },
  {
    "FOLIO": "38",
    "RESULTADO_AUDITORIA": "CARPETA VACÍA",
    "CALLE": "Jose Maria Gonzalez Arratia",
    "COLONIA": "Santa Clara",
    "DELEGACION": "CENTRO HISTÓRICO",
    "_company": "ROCADURA",
    "_stage": "E2"
  },
  {
    "FOLIO": "39",
    "RESULTADO_AUDITORIA": "CARPETA VACÍA",
    "CALLE": "Jose Maria Gonzalez Arratia",
    "COLONIA": "Santa Clara",
    "DELEGACION": "CENTRO HISTÓRICO",
    "_company": "ROCADURA",
    "_stage": "E2"
  },
  {
    "FOLIO": "40",
    "RESULTADO_AUDITORIA": "CARPETA VACÍA",
    "CALLE": "Jose Maria Gonzalez Arratia",
    "COLONIA": "Santa Clara",
    "DELEGACION": "CENTRO HISTÓRICO",
    "_company": "ROCADURA",
    "_stage": "E2"
  },
  {
    "FOLIO": "45",
    "RESULTADO_AUDITORIA": "FALTA: CAJA + FINAL",
    "CALLE": "Jose Maria Gonzalez Arratia",
    "COLONIA": "Santa Clara",
    "DELEGACION": "CENTRO HISTÓRICO",
    "_company": "ROCADURA",
    "_stage": "E2"
  },
  {
    "FOLIO": "46",
    "RESULTADO_AUDITORIA": "FALTA: CAJA + FINAL",
    "CALLE": "Jose Maria Gonzalez Arratia",
    "COLONIA": "Santa Clara",
    "DELEGACION": "CENTRO HISTÓRICO",
    "_company": "ROCADURA",
    "_stage": "E2"
  },
  {
    "FOLIO": "47",
    "RESULTADO_AUDITORIA": "FALTA: CAJA + FINAL",
    "CALLE": "Jose Maria Gonzalez Arratia",
    "COLONIA": "Santa Clara",
    "DELEGACION": "CENTRO HISTÓRICO",
    "_company": "ROCADURA",
    "_stage": "E2"
  },
  {
    "FOLIO": "54",
    "RESULTADO_AUDITORIA": "CARPETA VACÍA",
    "CALLE": "Jose Maria Gonzalez Arratia",
    "COLONIA": "Santa Clara",
    "DELEGACION": "CENTRO HISTÓRICO",
    "_company": "ROCADURA",
    "_stage": "E2"
  },
  {
    "FOLIO": "57",
    "RESULTADO_AUDITORIA": "CARPETA VACÍA",
    "CALLE": "Jose Maria Gonzalez Arratia",
    "COLONIA": "Santa Clara",
    "DELEGACION": "CENTRO HISTÓRICO",
    "_company": "ROCADURA",
    "_stage": "E2"
  },
  {
    "FOLIO": "58",
    "RESULTADO_AUDITORIA": "FALTA: INICIAL + CAJA",
    "CALLE": "Sor Juana Ines De La Cruz",
    "COLONIA": "Santa Clara",
    "DELEGACION": "CENTRO HISTÓRICO",
    "_company": "ROCADURA",
    "_stage": "E2"
  },
  {
    "FOLIO": "65",
    "RESULTADO_AUDITORIA": "FALTA: FINAL",
    "CALLE": "Miguel Hidalgo",
    "COLONIA": "Santa Clara",
    "DELEGACION": "CENTRO HISTÓRICO",
    "_company": "ROCADURA",
    "_stage": "E2"
  },
  {
    "FOLIO": "66",
    "RESULTADO_AUDITORIA": "FALTA: CAJA",
    "CALLE": "Miguel Hidalgo",
    "COLONIA": "Santa Clara",
    "DELEGACION": "CENTRO HISTÓRICO",
    "_company": "ROCADURA",
    "_stage": "E2"
  },
  {
    "FOLIO": "68",
    "RESULTADO_AUDITORIA": "CARPETA VACÍA",
    "CALLE": "Jose Vicente Villada",
    "COLONIA": "Francisco Murguía (El Ranchito)",
    "DELEGACION": "CENTRO HISTÓRICO",
    "_company": "ROCADURA",
    "_stage": "E2"
  },
  {
    "FOLIO": "72",
    "RESULTADO_AUDITORIA": "FALTA: CAJA + FINAL",
    "CALLE": "Jose Vicente Villada",
    "COLONIA": "Francisco Murguía (El Ranchito)",
    "DELEGACION": "CENTRO HISTÓRICO",
    "_company": "ROCADURA",
    "_stage": "E2"
  },
  {
    "FOLIO": "73",
    "RESULTADO_AUDITORIA": "FALTA: CAJA",
    "CALLE": "Jose Vicente Villada",
    "COLONIA": "Francisco Murguía (El Ranchito)",
    "DELEGACION": "CENTRO HISTÓRICO",
    "_company": "ROCADURA",
    "_stage": "E2"
  },
  {
    "FOLIO": "76",
    "RESULTADO_AUDITORIA": "FALTA: CAJA + FINAL",
    "CALLE": "Jose Vicente Villada",
    "COLONIA": "Centro",
    "DELEGACION": "CENTRO HISTÓRICO",
    "_company": "ROCADURA",
    "_stage": "E2"
  },
  {
    "FOLIO": "77",
    "RESULTADO_AUDITORIA": "FALTA: INICIAL + CAJA",
    "CALLE": "Eduardo Gonzalez Y Pichardo",
    "COLONIA": "La Merced (Alameda)",
    "DELEGACION": "CENTRO HISTÓRICO",
    "_company": "ROCADURA",
    "_stage": "E2"
  },
  {
    "FOLIO": "78",
    "RESULTADO_AUDITORIA": "CARPETA VACÍA",
    "CALLE": "Eduardo Gonzalez Y Pichardo",
    "COLONIA": "La Merced (Alameda)",
    "DELEGACION": "CENTRO HISTÓRICO",
    "_company": "ROCADURA",
    "_stage": "E2"
  },
  {
    "FOLIO": "79",
    "RESULTADO_AUDITORIA": "CARPETA VACÍA",
    "CALLE": "Eduardo Gonzalez Y Pichardo",
    "COLONIA": "La Merced (Alameda)",
    "DELEGACION": "CENTRO HISTÓRICO",
    "_company": "ROCADURA",
    "_stage": "E2"
  },
  {
    "FOLIO": "84",
    "RESULTADO_AUDITORIA": "FALTA: CAJA",
    "CALLE": "Eduardo Gonzalez Y Pichardo",
    "COLONIA": "La Merced (Alameda)",
    "DELEGACION": "CENTRO HISTÓRICO",
    "_company": "ROCADURA",
    "_stage": "E2"
  },
  {
    "FOLIO": "85",
    "RESULTADO_AUDITORIA": "FALTA: CAJA",
    "CALLE": "Eduardo Gonzalez Y Pichardo",
    "COLONIA": "La Merced (Alameda)",
    "DELEGACION": "CENTRO HISTÓRICO",
    "_company": "ROCADURA",
    "_stage": "E2"
  },
  {
    "FOLIO": "86",
    "RESULTADO_AUDITORIA": "CARPETA VACÍA",
    "CALLE": "Eduardo Gonzalez Y Pichardo",
    "COLONIA": "La Merced (Alameda)",
    "DELEGACION": "CENTRO HISTÓRICO",
    "_company": "ROCADURA",
    "_stage": "E2"
  },
  {
    "FOLIO": "87",
    "RESULTADO_AUDITORIA": "FALTA: INICIAL + FINAL",
    "CALLE": "Eduardo Gonzalez Y Pichardo",
    "COLONIA": "La Merced (Alameda)",
    "DELEGACION": "CENTRO HISTÓRICO",
    "_company": "ROCADURA",
    "_stage": "E2"
  },
  {
    "FOLIO": "88",
    "RESULTADO_AUDITORIA": "CARPETA VACÍA",
    "CALLE": "Eduardo Gonzalez Y Pichardo",
    "COLONIA": "La Merced (Alameda)",
    "DELEGACION": "CENTRO HISTÓRICO",
    "_company": "ROCADURA",
    "_stage": "E2"
  },
  {
    "FOLIO": "89",
    "RESULTADO_AUDITORIA": "FALTA: CAJA",
    "CALLE": "Eduardo Gonzalez Y Pichardo",
    "COLONIA": "La Merced (Alameda)",
    "DELEGACION": "CENTRO HISTÓRICO",
    "_company": "ROCADURA",
    "_stage": "E2"
  },
  {
    "FOLIO": "90",
    "RESULTADO_AUDITORIA": "FALTA: INICIAL + CAJA",
    "CALLE": "Eduardo Gonzalez Y Pichardo",
    "COLONIA": "La Merced (Alameda)",
    "DELEGACION": "CENTRO HISTÓRICO",
    "_company": "ROCADURA",
    "_stage": "E2"
  },
  {
    "FOLIO": "95",
    "RESULTADO_AUDITORIA": "FALTA: CAJA + FINAL",
    "CALLE": "Eduardo Gonzalez Y Pichardo",
    "COLONIA": "La Merced (Alameda)",
    "DELEGACION": "CENTRO HISTÓRICO",
    "_company": "ROCADURA",
    "_stage": "E2"
  },
  {
    "FOLIO": "98",
    "RESULTADO_AUDITORIA": "FALTA: CAJA",
    "CALLE": "Eduardo Gonzalez Y Pichardo",
    "COLONIA": "La Merced (Alameda)",
    "DELEGACION": "CENTRO HISTÓRICO",
    "_company": "ROCADURA",
    "_stage": "E2"
  },
  {
    "FOLIO": "99",
    "RESULTADO_AUDITORIA": "FALTA: INICIAL + CAJA",
    "CALLE": "Eduardo Gonzalez Y Pichardo",
    "COLONIA": "La Merced (Alameda)",
    "DELEGACION": "CENTRO HISTÓRICO",
    "_company": "ROCADURA",
    "_stage": "E2"
  },
  {
    "FOLIO": "100",
    "RESULTADO_AUDITORIA": "FALTA: CAJA",
    "CALLE": "Eduardo Gonzalez Y Pichardo",
    "COLONIA": "La Merced (Alameda)",
    "DELEGACION": "CENTRO HISTÓRICO",
    "_company": "ROCADURA",
    "_stage": "E2"
  },
  {
    "FOLIO": "101",
    "RESULTADO_AUDITORIA": "FALTA: INICIAL + CAJA",
    "CALLE": "Eduardo Gonzalez Y Pichardo",
    "COLONIA": "La Merced (Alameda)",
    "DELEGACION": "CENTRO HISTÓRICO",
    "_company": "ROCADURA",
    "_stage": "E2"
  },
  {
    "FOLIO": "102",
    "RESULTADO_AUDITORIA": "FALTA: CAJA",
    "CALLE": "Eduardo Gonzalez Y Pichardo",
    "COLONIA": "La Merced (Alameda)",
    "DELEGACION": "CENTRO HISTÓRICO",
    "_company": "ROCADURA",
    "_stage": "E2"
  },
  {
    "FOLIO": "103",
    "RESULTADO_AUDITORIA": "FALTA: INICIAL + CAJA",
    "CALLE": "Eduardo Gonzalez Y Pichardo",
    "COLONIA": "La Merced (Alameda)",
    "DELEGACION": "CENTRO HISTÓRICO",
    "_company": "ROCADURA",
    "_stage": "E2"
  },
  {
    "FOLIO": "104",
    "RESULTADO_AUDITORIA": "FALTA: CAJA",
    "CALLE": "Eduardo Gonzalez Y Pichardo",
    "COLONIA": "La Merced (Alameda)",
    "DELEGACION": "CENTRO HISTÓRICO",
    "_company": "ROCADURA",
    "_stage": "E2"
  },
  {
    "FOLIO": "105",
    "RESULTADO_AUDITORIA": "FALTA: INICIAL + CAJA",
    "CALLE": "Eduardo Gonzalez Y Pichardo",
    "COLONIA": "La Merced (Alameda)",
    "DELEGACION": "CENTRO HISTÓRICO",
    "_company": "ROCADURA",
    "_stage": "E2"
  },
  {
    "FOLIO": "107",
    "RESULTADO_AUDITORIA": "FALTA: CAJA",
    "CALLE": "Eduardo Gonzalez Y Pichardo",
    "COLONIA": "La Merced (Alameda)",
    "DELEGACION": "CENTRO HISTÓRICO",
    "_company": "ROCADURA",
    "_stage": "E2"
  },
  {
    "FOLIO": "108",
    "RESULTADO_AUDITORIA": "FALTA: INICIAL + CAJA",
    "CALLE": "Eduardo Gonzalez Y Pichardo",
    "COLONIA": "La Merced (Alameda)",
    "DELEGACION": "CENTRO HISTÓRICO",
    "_company": "ROCADURA",
    "_stage": "E2"
  },
  {
    "FOLIO": "109",
    "RESULTADO_AUDITORIA": "FALTA: INICIAL + CAJA",
    "CALLE": "Eduardo Gonzalez Y Pichardo",
    "COLONIA": "La Merced (Alameda)",
    "DELEGACION": "CENTRO HISTÓRICO",
    "_company": "ROCADURA",
    "_stage": "E2"
  },
  {
    "FOLIO": "110",
    "RESULTADO_AUDITORIA": "FALTA: INICIAL + CAJA",
    "CALLE": "Eduardo Gonzalez Y Pichardo",
    "COLONIA": "La Merced (Alameda)",
    "DELEGACION": "CENTRO HISTÓRICO",
    "_company": "ROCADURA",
    "_stage": "E2"
  },
  {
    "FOLIO": "111",
    "RESULTADO_AUDITORIA": "FALTA: INICIAL + CAJA",
    "CALLE": "Eduardo Gonzalez Y Pichardo",
    "COLONIA": "La Merced (Alameda)",
    "DELEGACION": "CENTRO HISTÓRICO",
    "_company": "ROCADURA",
    "_stage": "E2"
  },
  {
    "FOLIO": "112",
    "RESULTADO_AUDITORIA": "FALTA: INICIAL",
    "CALLE": "Eduardo Gonzalez Y Pichardo",
    "COLONIA": "La Merced (Alameda)",
    "DELEGACION": "CENTRO HISTÓRICO",
    "_company": "ROCADURA",
    "_stage": "E2"
  },
  {
    "FOLIO": "113",
    "RESULTADO_AUDITORIA": "FALTA: CAJA",
    "CALLE": "Eduardo Gonzalez Y Pichardo",
    "COLONIA": "La Merced (Alameda)",
    "DELEGACION": "CENTRO HISTÓRICO",
    "_company": "ROCADURA",
    "_stage": "E2"
  },
  {
    "FOLIO": "114",
    "RESULTADO_AUDITORIA": "FALTA: INICIAL + CAJA",
    "CALLE": "Eduardo Gonzalez Y Pichardo",
    "COLONIA": "La Merced (Alameda)",
    "DELEGACION": "CENTRO HISTÓRICO",
    "_company": "ROCADURA",
    "_stage": "E2"
  },
  {
    "FOLIO": "115",
    "RESULTADO_AUDITORIA": "FALTA: INICIAL + CAJA",
    "CALLE": "Eduardo Gonzalez Y Pichardo",
    "COLONIA": "La Merced (Alameda)",
    "DELEGACION": "CENTRO HISTÓRICO",
    "_company": "ROCADURA",
    "_stage": "E2"
  },
  {
    "FOLIO": "116",
    "RESULTADO_AUDITORIA": "FALTA: INICIAL + CAJA",
    "CALLE": "Eduardo Gonzalez Y Pichardo",
    "COLONIA": "La Merced (Alameda)",
    "DELEGACION": "CENTRO HISTÓRICO",
    "_company": "ROCADURA",
    "_stage": "E2"
  },
  {
    "FOLIO": "117",
    "RESULTADO_AUDITORIA": "FALTA: INICIAL + CAJA",
    "CALLE": "Eduardo Gonzalez Y Pichardo",
    "COLONIA": "La Merced (Alameda)",
    "DELEGACION": "CENTRO HISTÓRICO",
    "_company": "ROCADURA",
    "_stage": "E2"
  },
  {
    "FOLIO": "118",
    "RESULTADO_AUDITORIA": "FALTA: INICIAL + CAJA",
    "CALLE": "Eduardo Gonzalez Y Pichardo",
    "COLONIA": "La Merced (Alameda)",
    "DELEGACION": "CENTRO HISTÓRICO",
    "_company": "ROCADURA",
    "_stage": "E2"
  },
  {
    "FOLIO": "119",
    "RESULTADO_AUDITORIA": "FALTA: INICIAL + CAJA",
    "CALLE": "Eduardo Gonzalez Y Pichardo",
    "COLONIA": "La Merced (Alameda)",
    "DELEGACION": "CENTRO HISTÓRICO",
    "_company": "ROCADURA",
    "_stage": "E2"
  },
  {
    "FOLIO": "120",
    "RESULTADO_AUDITORIA": "FALTA: INICIAL",
    "CALLE": "Eduardo Gonzalez Y Pichardo",
    "COLONIA": "La Merced (Alameda)",
    "DELEGACION": "CENTRO HISTÓRICO",
    "_company": "ROCADURA",
    "_stage": "E2"
  },
  {
    "FOLIO": "121",
    "RESULTADO_AUDITORIA": "FALTA: INICIAL + CAJA",
    "CALLE": "Eduardo Gonzalez Y Pichardo",
    "COLONIA": "La Merced (Alameda)",
    "DELEGACION": "CENTRO HISTÓRICO",
    "_company": "ROCADURA",
    "_stage": "E2"
  },
  {
    "FOLIO": "122",
    "RESULTADO_AUDITORIA": "FALTA: INICIAL + CAJA",
    "CALLE": "Eduardo Gonzalez Y Pichardo",
    "COLONIA": "La Merced (Alameda)",
    "DELEGACION": "CENTRO HISTÓRICO",
    "_company": "ROCADURA",
    "_stage": "E2"
  },
  {
    "FOLIO": "124",
    "RESULTADO_AUDITORIA": "FALTA: CAJA",
    "CALLE": "Eduardo Gonzalez Y Pichardo",
    "COLONIA": "La Merced (Alameda)",
    "DELEGACION": "CENTRO HISTÓRICO",
    "_company": "ROCADURA",
    "_stage": "E2"
  },
  {
    "FOLIO": "125",
    "RESULTADO_AUDITORIA": "FALTA: INICIAL + CAJA",
    "CALLE": "Eduardo Gonzalez Y Pichardo",
    "COLONIA": "La Merced (Alameda)",
    "DELEGACION": "CENTRO HISTÓRICO",
    "_company": "ROCADURA",
    "_stage": "E2"
  },
  {
    "FOLIO": "126",
    "RESULTADO_AUDITORIA": "FALTA: INICIAL + CAJA",
    "CALLE": "Eduardo Gonzalez Y Pichardo",
    "COLONIA": "La Merced (Alameda)",
    "DELEGACION": "CENTRO HISTÓRICO",
    "_company": "ROCADURA",
    "_stage": "E2"
  },
  {
    "FOLIO": "127",
    "RESULTADO_AUDITORIA": "FALTA: INICIAL + CAJA",
    "CALLE": "Eduardo Gonzalez Y Pichardo",
    "COLONIA": "La Merced (Alameda)",
    "DELEGACION": "CENTRO HISTÓRICO",
    "_company": "ROCADURA",
    "_stage": "E2"
  },
  {
    "FOLIO": "128",
    "RESULTADO_AUDITORIA": "FALTA: CAJA",
    "CALLE": "Eduardo Gonzalez Y Pichardo",
    "COLONIA": "La Merced (Alameda)",
    "DELEGACION": "CENTRO HISTÓRICO",
    "_company": "ROCADURA",
    "_stage": "E2"
  },
  {
    "FOLIO": "129",
    "RESULTADO_AUDITORIA": "FALTA: INICIAL + CAJA",
    "CALLE": "Eduardo Gonzalez Y Pichardo",
    "COLONIA": "La Merced (Alameda)",
    "DELEGACION": "CENTRO HISTÓRICO",
    "_company": "ROCADURA",
    "_stage": "E2"
  },
  {
    "FOLIO": "130",
    "RESULTADO_AUDITORIA": "FALTA: CAJA",
    "CALLE": "Eduardo Gonzalez Y Pichardo",
    "COLONIA": "La Merced (Alameda)",
    "DELEGACION": "CENTRO HISTÓRICO",
    "_company": "ROCADURA",
    "_stage": "E2"
  },
  {
    "FOLIO": "131",
    "RESULTADO_AUDITORIA": "FALTA: INICIAL + CAJA",
    "CALLE": "Eduardo Gonzalez Y Pichardo",
    "COLONIA": "La Merced (Alameda)",
    "DELEGACION": "CENTRO HISTÓRICO",
    "_company": "ROCADURA",
    "_stage": "E2"
  },
  {
    "FOLIO": "132",
    "RESULTADO_AUDITORIA": "FALTA: INICIAL + CAJA",
    "CALLE": "Eduardo Gonzalez Y Pichardo",
    "COLONIA": "La Merced (Alameda)",
    "DELEGACION": "CENTRO HISTÓRICO",
    "_company": "ROCADURA",
    "_stage": "E2"
  },
  {
    "FOLIO": "133",
    "RESULTADO_AUDITORIA": "FALTA: INICIAL",
    "CALLE": "Eduardo Gonzalez Y Pichardo",
    "COLONIA": "La Merced (Alameda)",
    "DELEGACION": "CENTRO HISTÓRICO",
    "_company": "ROCADURA",
    "_stage": "E2"
  },
  {
    "FOLIO": "134",
    "RESULTADO_AUDITORIA": "FALTA: CAJA",
    "CALLE": "Eduardo Gonzalez Y Pichardo",
    "COLONIA": "La Merced (Alameda)",
    "DELEGACION": "CENTRO HISTÓRICO",
    "_company": "ROCADURA",
    "_stage": "E2"
  },
  {
    "FOLIO": "34001",
    "RESULTADO_AUDITORIA": "FALTA: INICIAL",
    "CALLE": "Filiberto Navas",
    "COLONIA": "Tierra y Libertad",
    "DELEGACION": "SAN MATEO OXTOTITLAN",
    "_company": "ROCADURA",
    "_stage": "E2"
  },
  {
    "FOLIO": "34020",
    "RESULTADO_AUDITORIA": "FALTA: INICIAL",
    "CALLE": "Filiberto Navas",
    "COLONIA": "Tierra y Libertad",
    "DELEGACION": "SAN MATEO OXTOTITLAN",
    "_company": "ROCADURA",
    "_stage": "E2"
  },
  {
    "FOLIO": "34138",
    "RESULTADO_AUDITORIA": "FALTA: INICIAL",
    "CALLE": "Filiberto Navas",
    "COLONIA": "Niños Héroes II",
    "DELEGACION": "SAN MATEO OXTOTITLAN",
    "_company": "ROCADURA",
    "_stage": "E2"
  },
  {
    "FOLIO": "34145",
    "RESULTADO_AUDITORIA": "FALTA: INICIAL",
    "CALLE": "San Miguel",
    "COLONIA": "San Jorge",
    "DELEGACION": "SAN MATEO OXTOTITLAN",
    "_company": "ROCADURA",
    "_stage": "E2"
  }
]