[
  {
    "FOLIO": "170001",
    "RESULTADO_AUDITORIA": "OK",
    "CALLE": "SAN JUAN",
    "COLONIA": "PLAZAS DE  SAN BUENAVENTURA",
    "DELEGACION": "CIUDAD UNIVERSITARIA",
    "_company": "EDIT",
    "_stage": "E3",
    "_folderId": "1APk9fpPQfnPz77LTCjp_RfBmfC8fK-BD",
    "PHOTOS": {
      "INICIAL": {
        "thumbnail": "https://lh3.googleusercontent.com/drive-storage/AJQWtBMkhSoFhCnKCaRDOQ2i59RteZNRU_4aebwFS5lZ21lFgm9S6EYwC2m-2p9ZKrC-uAEk-MQ7r2Ed1QVE1NBlGSozEQwwENztUPsAa38SgvSqNR2X5z4=s220",
        "view": "https://drive.google.com/file/d/1pm9Y3_Oe0GgWz7fW9kQ2BqLQLkVzAa5E/view?usp=drivesdk"
      },
      "CAJA": {
        "thumbnail": "https://lh3.googleusercontent.com/drive-storage/AJQWtBM_Dhldt7c0yDjLrsi-1ECxGf4ORB0OmTOeFS2L5-0CYS63fRmj5aU60ytgFX-HTFmsV7TElUQStm5UcvkAJSUfDi_i6H_BzuXEwEkSkBkrfGk_Irw=s220",
        "view": "https://drive.google.com/file/d/1P0i32QXfisFLv2wldWBlVFyFSX40j2CR/view?usp=drivesdk"
      },
      "FINAL": {
        "thumbnail": "https://lh3.googleusercontent.com/drive-storage/AJQWtBNbMsTZ5y_-0m7eyddmEsL-Mss5bzTonPqdil-5Xdr6bxfhKb0VPDkBozRRq2U5gkwDcezL81x_ZsKZ6iHIeRLiPw6kYquGHQHn8VmjOmhzwVHdmRQ=s220",
        "view": "https://drive.google.com/file/d/1q_JQe672q3aFJoC08wgluUbhVHAjUeuu/view?usp=drivesdk"
      }
    }
  },
  {
    "FOLIO": "170002",
    "RESULTADO_AUDITORIA": "SIN CARPETA",
    "CALLE": "SAN JUAN",
    "COLONIA": "PLAZAS DE  SAN BUENAVENTURA",
    "DELEGACION": "CIUDAD UNIVERSITARIA",
    "_company": "EDIT",
    "_stage": "E3",
    "_folderId": null,
    "PHOTOS": null
  },
  {
    "FOLIO": "170003",
    "RESULTADO_AUDITORIA": "SIN CARPETA",
    "CALLE": "SAN JUAN",
    "COLONIA": "PLAZAS DE  SAN BUENAVENTURA",
    "DELEGACION": "CIUDAD UNIVERSITARIA",
    "_company": "EDIT",
    "_stage": "E3",
    "_folderId": null,
    "PHOTOS": null
  },
  {
    "FOLIO": "170004",
    "RESULTADO_AUDITORIA": "SIN CARPETA",
    "CALLE": "SAN JUAN",
    "COLONIA": "PLAZAS DE  SAN BUENAVENTURA",
    "DELEGACION": "CIUDAD UNIVERSITARIA",
    "_company": "EDIT",
    "_stage": "E3",
    "_folderId": null,
    "PHOTOS": null
  },
  {
    "FOLIO": "170005",
    "RESULTADO_AUDITORIA": "SIN CARPETA",
    "CALLE": "SAN JUAN",
    "COLONIA": "PLAZAS DE  SAN BUENAVENTURA",
    "DELEGACION": "CIUDAD UNIVERSITARIA",
    "_company": "EDIT",
    "_stage": "E3",
    "_folderId": null,
    "PHOTOS": null
  },
  {
    "FOLIO": "170006",
    "RESULTADO_AUDITORIA": "SIN CARPETA",
    "CALLE": "SAN JUAN",
    "COLONIA": "PLAZAS DE  SAN BUENAVENTURA",
    "DELEGACION": "CIUDAD UNIVERSITARIA",
    "_company": "EDIT",
    "_stage": "E3",
    "_folderId": null,
    "PHOTOS": null
  },
  {
    "FOLIO": "170007",
    "RESULTADO_AUDITORIA": "SIN CARPETA",
    "CALLE": "SAN JUAN",
    "COLONIA": "PLAZAS DE  SAN BUENAVENTURA",
    "DELEGACION": "CIUDAD UNIVERSITARIA",
    "_company": "EDIT",
    "_stage": "E3",
    "_folderId": null,
    "PHOTOS": null
  },
  {
    "FOLIO": "170008",
    "RESULTADO_AUDITORIA": "SIN CARPETA",
    "CALLE": "SAN JUAN",
    "COLONIA": "PLAZAS DE  SAN BUENAVENTURA",
    "DELEGACION": "CIUDAD UNIVERSITARIA",
    "_company": "EDIT",
    "_stage": "E3",
    "_folderId": null,
    "PHOTOS": null
  },
  {
    "FOLIO": "170009",
    "RESULTADO_AUDITORIA": "SIN CARPETA",
    "CALLE": "SAN JUAN",
    "COLONIA": "PLAZAS DE  SAN BUENAVENTURA",
    "DELEGACION": "CIUDAD UNIVERSITARIA",
    "_company": "EDIT",
    "_stage": "E3",
    "_folderId": null,
    "PHOTOS": null
  },
  {
    "FOLIO": "170010",
    "RESULTADO_AUDITORIA": "SIN CARPETA",
    "CALLE": "SAN JUAN",
    "COLONIA": "PLAZAS DE  SAN BUENAVENTURA",
    "DELEGACION": "CIUDAD UNIVERSITARIA",
    "_company": "EDIT",
    "_stage": "E3",
    "_folderId": null,
    "PHOTOS": null
  },
  {
    "FOLIO": "170011",
    "RESULTADO_AUDITORIA": "SIN CARPETA",
    "CALLE": "SAN JUAN",
    "COLONIA": "PLAZAS DE  SAN BUENAVENTURA",
    "DELEGACION": "CIUDAD UNIVERSITARIA",
    "_company": "EDIT",
    "_stage": "E3",
    "_folderId": null,
    "PHOTOS": null
  },
  {
    "FOLIO": "170012",
    "RESULTADO_AUDITORIA": "SIN CARPETA",
    "CALLE": "SAN JUAN",
    "COLONIA": "PLAZAS DE  SAN BUENAVENTURA",
    "DELEGACION": "CIUDAD UNIVERSITARIA",
    "_company": "EDIT",
    "_stage": "E3",
    "_folderId": null,
    "PHOTOS": null
  },
  {
    "FOLIO": "170013",
    "RESULTADO_AUDITORIA": "SIN CARPETA",
    "CALLE": "PROL. PASEO DE SAN BUENAVENTURA",
    "COLONIA": "PLAZAS DE  SAN BUENAVENTURA",
    "DELEGACION": "CIUDAD UNIVERSITARIA",
    "_company": "EDIT",
    "_stage": "E3",
    "_folderId": null,
    "PHOTOS": null
  },
  {
    "FOLIO": "170014",
    "RESULTADO_AUDITORIA": "SIN CARPETA",
    "CALLE": "PROL. PASEO DE SAN BUENAVENTURA",
    "COLONIA": "PLAZAS DE  SAN BUENAVENTURA",
    "DELEGACION": "CIUDAD UNIVERSITARIA",
    "_company": "EDIT",
    "_stage": "E3",
    "_folderId": null,
    "PHOTOS": null
  },
  {
    "FOLIO": "170015",
    "RESULTADO_AUDITORIA": "SIN CARPETA",
    "CALLE": "PROL. PASEO DE SAN BUENAVENTURA",
    "COLONIA": "PLAZAS DE  SAN BUENAVENTURA",
    "DELEGACION": "CIUDAD UNIVERSITARIA",
    "_company": "EDIT",
    "_stage": "E3",
    "_folderId": null,
    "PHOTOS": null
  },
  {
    "FOLIO": "170016",
    "RESULTADO_AUDITORIA": "SIN CARPETA",
    "CALLE": "PROL. PASEO DE SAN BUENAVENTURA",
    "COLONIA": "PLAZAS DE  SAN BUENAVENTURA",
    "DELEGACION": "CIUDAD UNIVERSITARIA",
    "_company": "EDIT",
    "_stage": "E3",
    "_folderId": null,
    "PHOTOS": null
  },
  {
    "FOLIO": "170017",
    "RESULTADO_AUDITORIA": "SIN CARPETA",
    "CALLE": "PROL. PASEO DE SAN BUENAVENTURA",
    "COLONIA": "PLAZAS DE  SAN BUENAVENTURA",
    "DELEGACION": "CIUDAD UNIVERSITARIA",
    "_company": "EDIT",
    "_stage": "E3",
    "_folderId": null,
    "PHOTOS": null
  },
  {
    "FOLIO": "170018",
    "RESULTADO_AUDITORIA": "SIN CARPETA",
    "CALLE": "PROL. PASEO DE SAN BUENAVENTURA",
    "COLONIA": "PLAZAS DE  SAN BUENAVENTURA",
    "DELEGACION": "CIUDAD UNIVERSITARIA",
    "_company": "EDIT",
    "_stage": "E3",
    "_folderId": null,
    "PHOTOS": null
  },
  {
    "FOLIO": "170019",
    "RESULTADO_AUDITORIA": "SIN CARPETA",
    "CALLE": "PROL. PASEO DE SAN BUENAVENTURA",
    "COLONIA": "PLAZAS DE  SAN BUENAVENTURA",
    "DELEGACION": "CIUDAD UNIVERSITARIA",
    "_company": "EDIT",
    "_stage": "E3",
    "_folderId": null,
    "PHOTOS": null
  },
  {
    "FOLIO": "170020",
    "RESULTADO_AUDITORIA": "SIN CARPETA",
    "CALLE": "PROL. PASEO DE SAN BUENAVENTURA",
    "COLONIA": "PLAZAS DE  SAN BUENAVENTURA",
    "DELEGACION": "CIUDAD UNIVERSITARIA",
    "_company": "EDIT",
    "_stage": "E3",
    "_folderId": null,
    "PHOTOS": null
  },
  {
    "FOLIO": "170021",
    "RESULTADO_AUDITORIA": "SIN CARPETA",
    "CALLE": "PROL. PASEO DE SAN BUENAVENTURA",
    "COLONIA": "PLAZAS DE  SAN BUENAVENTURA",
    "DELEGACION": "CIUDAD UNIVERSITARIA",
    "_company": "EDIT",
    "_stage": "E3",
    "_folderId": null,
    "PHOTOS": null
  },
  {
    "FOLIO": "170022",
    "RESULTADO_AUDITORIA": "SIN CARPETA",
    "CALLE": "PROL. PASEO DE SAN BUENAVENTURA",
    "COLONIA": "PLAZAS DE  SAN BUENAVENTURA",
    "DELEGACION": "CIUDAD UNIVERSITARIA",
    "_company": "EDIT",
    "_stage": "E3",
    "_folderId": null,
    "PHOTOS": null
  },
  {
    "FOLIO": "170023",
    "RESULTADO_AUDITORIA": "SIN CARPETA",
    "CALLE": "PROL. PASEO DE SAN BUENAVENTURA",
    "COLONIA": "PLAZAS DE  SAN BUENAVENTURA",
    "DELEGACION": "CIUDAD UNIVERSITARIA",
    "_company": "EDIT",
    "_stage": "E3",
    "_folderId": null,
    "PHOTOS": null
  },
  {
    "FOLIO": "170024",
    "RESULTADO_AUDITORIA": "SIN CARPETA",
    "CALLE": "PROL. PASEO DE SAN BUENAVENTURA",
    "COLONIA": "PLAZAS DE  SAN BUENAVENTURA",
    "DELEGACION": "CIUDAD UNIVERSITARIA",
    "_company": "EDIT",
    "_stage": "E3",
    "_folderId": null,
    "PHOTOS": null
  },
  {
    "FOLIO": "170025",
    "RESULTADO_AUDITORIA": "SIN CARPETA",
    "CALLE": "PROL. PASEO DE SAN BUENAVENTURA",
    "COLONIA": "PLAZAS DE  SAN BUENAVENTURA",
    "DELEGACION": "CIUDAD UNIVERSITARIA",
    "_company": "EDIT",
    "_stage": "E3",
    "_folderId": null,
    "PHOTOS": null
  },
  {
    "FOLIO": "170026",
    "RESULTADO_AUDITORIA": "SIN CARPETA",
    "CALLE": "PROL. PASEO DE SAN BUENAVENTURA",
    "COLONIA": "PLAZAS DE  SAN BUENAVENTURA",
    "DELEGACION": "CIUDAD UNIVERSITARIA",
    "_company": "EDIT",
    "_stage": "E3",
    "_folderId": null,
    "PHOTOS": null
  },
  {
    "FOLIO": "170027",
    "RESULTADO_AUDITORIA": "SIN CARPETA",
    "CALLE": "PROL. PASEO DE SAN BUENAVENTURA",
    "COLONIA": "PLAZAS DE  SAN BUENAVENTURA",
    "DELEGACION": "CIUDAD UNIVERSITARIA",
    "_company": "EDIT",
    "_stage": "E3",
    "_folderId": null,
    "PHOTOS": null
  },
  {
    "FOLIO": "170028",
    "RESULTADO_AUDITORIA": "SIN CARPETA",
    "CALLE": "PROL. PASEO DE SAN BUENAVENTURA",
    "COLONIA": "PLAZAS DE  SAN BUENAVENTURA",
    "DELEGACION": "CIUDAD UNIVERSITARIA",
    "_company": "EDIT",
    "_stage": "E3",
    "_folderId": null,
    "PHOTOS": null
  },
  {
    "FOLIO": "170029",
    "RESULTADO_AUDITORIA": "SIN CARPETA",
    "CALLE": "PROL. PASEO DE SAN BUENAVENTURA",
    "COLONIA": "PLAZAS DE  SAN BUENAVENTURA",
    "DELEGACION": "CIUDAD UNIVERSITARIA",
    "_company": "EDIT",
    "_stage": "E3",
    "_folderId": null,
    "PHOTOS": null
  },
  {
    "FOLIO": "170030",
    "RESULTADO_AUDITORIA": "SIN CARPETA",
    "CALLE": "PROL. PASEO DE SAN BUENAVENTURA",
    "COLONIA": "PLAZAS DE  SAN BUENAVENTURA",
    "DELEGACION": "CIUDAD UNIVERSITARIA",
    "_company": "EDIT",
    "_stage": "E3",
    "_folderId": null,
    "PHOTOS": null
  },
  {
    "FOLIO": "170031",
    "RESULTADO_AUDITORIA": "SIN CARPETA",
    "CALLE": "SAN JAVIER",
    "COLONIA": "PLAZAS DE  SAN BUENAVENTURA",
    "DELEGACION": "CIUDAD UNIVERSITARIA",
    "_company": "EDIT",
    "_stage": "E3",
    "_folderId": null,
    "PHOTOS": null
  },
  {
    "FOLIO": "170032",
    "RESULTADO_AUDITORIA": "SIN CARPETA",
    "CALLE": "SAN JAVIER",
    "COLONIA": "PLAZAS DE  SAN BUENAVENTURA",
    "DELEGACION": "CIUDAD UNIVERSITARIA",
    "_company": "EDIT",
    "_stage": "E3",
    "_folderId": null,
    "PHOTOS": null
  },
  {
    "FOLIO": "170033",
    "RESULTADO_AUDITORIA": "SIN CARPETA",
    "CALLE": "SAN JAVIER",
    "COLONIA": "PLAZAS DE  SAN BUENAVENTURA",
    "DELEGACION": "CIUDAD UNIVERSITARIA",
    "_company": "EDIT",
    "_stage": "E3",
    "_folderId": null,
    "PHOTOS": null
  },
  {
    "FOLIO": "170034",
    "RESULTADO_AUDITORIA": "SIN CARPETA",
    "CALLE": "SAN JAVIER",
    "COLONIA": "PLAZAS DE  SAN BUENAVENTURA",
    "DELEGACION": "CIUDAD UNIVERSITARIA",
    "_company": "EDIT",
    "_stage": "E3",
    "_folderId": null,
    "PHOTOS": null
  },
  {
    "FOLIO": "170035",
    "RESULTADO_AUDITORIA": "SIN CARPETA",
    "CALLE": "SAN JAVIER",
    "COLONIA": "PLAZAS DE  SAN BUENAVENTURA",
    "DELEGACION": "CIUDAD UNIVERSITARIA",
    "_company": "EDIT",
    "_stage": "E3",
    "_folderId": null,
    "PHOTOS": null
  },
  {
    "FOLIO": "170036",
    "RESULTADO_AUDITORIA": "OK",
    "CALLE": "SAN JAVIER",
    "COLONIA": "PLAZAS DE  SAN BUENAVENTURA",
    "DELEGACION": "CIUDAD UNIVERSITARIA",
    "_company": "EDIT",
    "_stage": "E3",
    "_folderId": "1ClNIUuZITDK3OmZEBLkwb6uuoGJUKOPl",
    "PHOTOS": {
      "INICIAL": {
        "thumbnail": "https://lh3.googleusercontent.com/drive-storage/AJQWtBPjhG0Cxo0qJpVN-os76emseuzlTktckpUTUz39kqwevRXW1MCniOj16HgbyLDVaGRjfGQ4yj0upPPD5T9NP25fvaWR-4Q97ynrgwKpuT-egH8x2HU=s220",
        "view": "https://drive.google.com/file/d/1nexzOAQF5tqJy5rAOx1LviNoIUk0MwWP/view?usp=drivesdk"
      },
      "CAJA": {
        "thumbnail": "https://lh3.googleusercontent.com/drive-storage/AJQWtBNDPAHUD8nwi5sv0oymemk2MRxUsrFV0H_Bs9StY8hqi1LozBX58kh9xnL85Fg4-8HK8qwaJXaz4o2C_PP_XAzO1jQLpG9ILDcy3W10B71Z-IakXyc=s220",
        "view": "https://drive.google.com/file/d/1_mVAU-XJ1w6cB1DAknvs9fGPn8ysT69i/view?usp=drivesdk"
      },
      "FINAL": {
        "thumbnail": "https://lh3.googleusercontent.com/drive-storage/AJQWtBMRMg0oratHBmvflb09_GaVJ04J-qKACmHLPiocd3wBf-ebDaJVjyum2DmzHwvF0XjobnJMkfdoRfpcJajHiXKZVXLFVfevnyjkyi956DBhj3uyy9g=s220",
        "view": "https://drive.google.com/file/d/1TvKCK-wBpgOce7-Ar7s9xi5h0lcYRomR/view?usp=drivesdk"
      }
    }
  },
  {
    "FOLIO": "170037",
    "RESULTADO_AUDITORIA": "OK",
    "CALLE": "SAN JAVIER",
    "COLONIA": "PLAZAS DE  SAN BUENAVENTURA",
    "DELEGACION": "CIUDAD UNIVERSITARIA",
    "_company": "EDIT",
    "_stage": "E3",
    "_folderId": "1wzwcqKbjc8HX2EkKPJ6aXDLEBt38hj5V",
    "PHOTOS": {
      "INICIAL": {
        "thumbnail": "https://lh3.googleusercontent.com/drive-storage/AJQWtBNXHkgLn6j4kWSPH3jEipzPnMGielrP67aiB9ENTb2Ir9d69iGrsdQ82TScHwXShr261A4Xb7nYznGswn5Mn8ZZyigxD77WLroR0zJQUGwly5wr7Ec=s220",
        "view": "https://drive.google.com/file/d/1z-dS9ny2VTKsN1ABXRge8xyXzRLANO2Z/view?usp=drivesdk"
      },
      "CAJA": {
        "thumbnail": "https://lh3.googleusercontent.com/drive-storage/AJQWtBNRzra6-zaEHHK765inAvhEomHRc_rc9OBe1Og6ED_q7_7OCiPVqShPM1EuZg9Ccd-J7WujEX-3qDMgA4WhoNS851ZCTMwpkT_afbXGMAf1qefl1XQ=s220",
        "view": "https://drive.google.com/file/d/13VW6dAoq1za1vVX3IeDhWiaPEJKqbFtR/view?usp=drivesdk"
      },
      "FINAL": {
        "thumbnail": "https://lh3.googleusercontent.com/drive-storage/AJQWtBNpdoSmLDq2pUNqzZ5Aph-Ibtes0yN1QfLjUMq2HcL4VzA1zCxvk9PSraNMIyUXbu3K3nAlFY7k_2YP4CCiuFvvXZKdw9TABZ0pwuhYElEN2sp6NfQ=s220",
        "view": "https://drive.google.com/file/d/1a9kRmryCQhBsDbWJBO2sZsLJFZuljKHz/view?usp=drivesdk"
      }
    }
  },
  {
    "FOLIO": "170038",
    "RESULTADO_AUDITORIA": "OK",
    "CALLE": "SAN JAVIER",
    "COLONIA": "PLAZAS DE  SAN BUENAVENTURA",
    "DELEGACION": "CIUDAD UNIVERSITARIA",
    "_company": "EDIT",
    "_stage": "E3",
    "_folderId": "1tloUqFgTB0sRZ5qPnwJkgeRQTjUUCwU8",
    "PHOTOS": {
      "INICIAL": {
        "thumbnail": "https://lh3.googleusercontent.com/drive-storage/AJQWtBPyI1nxyAOL8VEu58WZHM7ULv6LQtnvEP3XQFTkg7kaXIQDlNZLCLdf8jZbRCaunMznDfUdFkuz9LAiGvQuShkOjDCSOvGq7panFJyIaBnD_sHGheM=s220",
        "view": "https://drive.google.com/file/d/1h738q3dpwCW86Bee0oPNPBEqzpCs4M1t/view?usp=drivesdk"
      },
      "CAJA": {
        "thumbnail": "https://lh3.googleusercontent.com/drive-storage/AJQWtBPRFeLxtPfU38voGN45LQqT8wbv3nC1LQVIrOjzvlAUo2p5Y--5arsK-zdiP-IIayFSM1-a0KacS6UJjLBKNePx5C6MVLkOICsSz4pqcUg-BoxXGmg=s220",
        "view": "https://drive.google.com/file/d/153ecWANGBs8ybl1N0cFufIZpczQf6C4g/view?usp=drivesdk"
      },
      "FINAL": {
        "thumbnail": "https://lh3.googleusercontent.com/drive-storage/AJQWtBP8TlXYofpGUfqIhpL1NkmGRCvAZq0nj-FiyUnttf2bemAv3Vh6l6TfyCIfDeI81nsjlWt4xXurMKE-UGaZ-LPtythYf9WHsALuODpZKqv9Tpkn6H0=s220",
        "view": "https://drive.google.com/file/d/1sJ5NeQ1Sl48xXXGCiB_9f7X4wXm6alGn/view?usp=drivesdk"
      }
    }
  },
  {
    "FOLIO": "170039",
    "RESULTADO_AUDITORIA": "OK",
    "CALLE": "SAN JAVIER",
    "COLONIA": "PLAZAS DE  SAN BUENAVENTURA",
    "DELEGACION": "CIUDAD UNIVERSITARIA",
    "_company": "EDIT",
    "_stage": "E3",
    "_folderId": "1Sg7gW49UIzG088iI9lsiGufqkc2E41GI",
    "PHOTOS": {
      "INICIAL": {
        "thumbnail": "https://lh3.googleusercontent.com/drive-storage/AJQWtBOkUb-4k_fzPDQGa2HYeKafPJzy1TnWxev_D7vqjKmIH8Cbdg-i8_cKElAegLr4vAnoih8FyPYqr2nEJE5SK5YroV-bYX4okp9Y-3SSAr24jr69_-I=s220",
        "view": "https://drive.google.com/file/d/1Yne7WOnOdRT0nQRUmAhIpJVzx5xRwWpr/view?usp=drivesdk"
      },
      "CAJA": {
        "thumbnail": "https://lh3.googleusercontent.com/drive-storage/AJQWtBOx0ukD_DcXCH7MVqt3l0LUI8JpFmeG8iPMEyIoyohSTClcDOJcyHs_j7LiWpzZIJQh1oYPAUen4dJFiLKjPg5zBlrv0_gwnEOxAkacqpsx3ZXET5c=s220",
        "view": "https://drive.google.com/file/d/1XxtsViNY0iVOGs7U6RFE-AouMlI2e1PP/view?usp=drivesdk"
      },
      "FINAL": {
        "thumbnail": "https://lh3.googleusercontent.com/drive-storage/AJQWtBPCq5hTU-7J_O286pWJFR6yDHVzTSkRBkZOcsQ5ciRo9R_W3GA7tjaXxgHtrDgSS_EqpiqPOUNF-481I-otqFYIkdMFD3pz2Ww5n0k9fSj1iVR3Qyw=s220",
        "view": "https://drive.google.com/file/d/13ZttTSquXaKD6rFpdgWdejOGKSXi5W47/view?usp=drivesdk"
      }
    }
  },
  {
    "FOLIO": "170040",
    "RESULTADO_AUDITORIA": "SIN CARPETA",
    "CALLE": "SAN JAVIER",
    "COLONIA": "PLAZAS DE  SAN BUENAVENTURA",
    "DELEGACION": "CIUDAD UNIVERSITARIA",
    "_company": "EDIT",
    "_stage": "E3",
    "_folderId": null,
    "PHOTOS": null
  },
  {
    "FOLIO": "170041",
    "RESULTADO_AUDITORIA": "SIN CARPETA",
    "CALLE": "SAN JAVIER",
    "COLONIA": "PLAZAS DE  SAN BUENAVENTURA",
    "DELEGACION": "CIUDAD UNIVERSITARIA",
    "_company": "EDIT",
    "_stage": "E3",
    "_folderId": null,
    "PHOTOS": null
  },
  {
    "FOLIO": "170042",
    "RESULTADO_AUDITORIA": "SIN CARPETA",
    "CALLE": "SAN JAVIER",
    "COLONIA": "PLAZAS DE  SAN BUENAVENTURA",
    "DELEGACION": "CIUDAD UNIVERSITARIA",
    "_company": "EDIT",
    "_stage": "E3",
    "_folderId": null,
    "PHOTOS": null
  },
  {
    "FOLIO": "170043",
    "RESULTADO_AUDITORIA": "SIN CARPETA",
    "CALLE": "SAN JAVIER",
    "COLONIA": "PLAZAS DE  SAN BUENAVENTURA",
    "DELEGACION": "CIUDAD UNIVERSITARIA",
    "_company": "EDIT",
    "_stage": "E3",
    "_folderId": null,
    "PHOTOS": null
  },
  {
    "FOLIO": "170044",
    "RESULTADO_AUDITORIA": "SIN CARPETA",
    "CALLE": "SAN JAVIER",
    "COLONIA": "PLAZAS DE  SAN BUENAVENTURA",
    "DELEGACION": "CIUDAD UNIVERSITARIA",
    "_company": "EDIT",
    "_stage": "E3",
    "_folderId": null,
    "PHOTOS": null
  },
  {
    "FOLIO": "170045",
    "RESULTADO_AUDITORIA": "SIN CARPETA",
    "CALLE": "SAN JAVIER",
    "COLONIA": "PLAZAS DE  SAN BUENAVENTURA",
    "DELEGACION": "CIUDAD UNIVERSITARIA",
    "_company": "EDIT",
    "_stage": "E3",
    "_folderId": null,
    "PHOTOS": null
  },
  {
    "FOLIO": "170046",
    "RESULTADO_AUDITORIA": "SIN CARPETA",
    "CALLE": "SAN JAVIER",
    "COLONIA": "PLAZAS DE  SAN BUENAVENTURA",
    "DELEGACION": "CIUDAD UNIVERSITARIA",
    "_company": "EDIT",
    "_stage": "E3",
    "_folderId": null,
    "PHOTOS": null
  },
  {
    "FOLIO": "170047",
    "RESULTADO_AUDITORIA": "SIN CARPETA",
    "CALLE": "SAN JAVIER",
    "COLONIA": "PLAZAS DE  SAN BUENAVENTURA",
    "DELEGACION": "CIUDAD UNIVERSITARIA",
    "_company": "EDIT",
    "_stage": "E3",
    "_folderId": null,
    "PHOTOS": null
  },
  {
    "FOLIO": "170048",
    "RESULTADO_AUDITORIA": "SIN CARPETA",
    "CALLE": "SAN JAVIER",
    "COLONIA": "PLAZAS DE  SAN BUENAVENTURA",
    "DELEGACION": "CIUDAD UNIVERSITARIA",
    "_company": "EDIT",
    "_stage": "E3",
    "_folderId": null,
    "PHOTOS": null
  },
  {
    "FOLIO": "170049",
    "RESULTADO_AUDITORIA": "SIN CARPETA",
    "CALLE": "SAN JAVIER",
    "COLONIA": "PLAZAS DE  SAN BUENAVENTURA",
    "DELEGACION": "CIUDAD UNIVERSITARIA",
    "_company": "EDIT",
    "_stage": "E3",
    "_folderId": null,
    "PHOTOS": null
  },
  {
    "FOLIO": "170050",
    "RESULTADO_AUDITORIA": "SIN CARPETA",
    "CALLE": "SAN JAVIER",
    "COLONIA": "PLAZAS DE  SAN BUENAVENTURA",
    "DELEGACION": "CIUDAD UNIVERSITARIA",
    "_company": "EDIT",
    "_stage": "E3",
    "_folderId": null,
    "PHOTOS": null
  },
  {
    "FOLIO": "170051",
    "RESULTADO_AUDITORIA": "SIN CARPETA",
    "CALLE": "SAN JAVIER",
    "COLONIA": "PLAZAS DE  SAN BUENAVENTURA",
    "DELEGACION": "CIUDAD UNIVERSITARIA",
    "_company": "EDIT",
    "_stage": "E3",
    "_folderId": null,
    "PHOTOS": null
  },
  {
    "FOLIO": "170052",
    "RESULTADO_AUDITORIA": "SIN CARPETA",
    "CALLE": "SAN JAVIER",
    "COLONIA": "PLAZAS DE  SAN BUENAVENTURA",
    "DELEGACION": "CIUDAD UNIVERSITARIA",
    "_company": "EDIT",
    "_stage": "E3",
    "_folderId": null,
    "PHOTOS": null
  },
  {
    "FOLIO": "170053",
    "RESULTADO_AUDITORIA": "SIN CARPETA",
    "CALLE": "SAN JAVIER",
    "COLONIA": "PLAZAS DE  SAN BUENAVENTURA",
    "DELEGACION": "CIUDAD UNIVERSITARIA",
    "_company": "EDIT",
    "_stage": "E3",
    "_folderId": null,
    "PHOTOS": null
  },
  {
    "FOLIO": "170054",
    "RESULTADO_AUDITORIA": "SIN CARPETA",
    "CALLE": "SAN JAVIER",
    "COLONIA": "PLAZAS DE  SAN BUENAVENTURA",
    "DELEGACION": "CIUDAD UNIVERSITARIA",
    "_company": "EDIT",
    "_stage": "E3",
    "_folderId": null,
    "PHOTOS": null
  },
  {
    "FOLIO": "170055",
    "RESULTADO_AUDITORIA": "SIN CARPETA",
    "CALLE": "SAN JAVIER",
    "COLONIA": "PLAZAS DE  SAN BUENAVENTURA",
    "DELEGACION": "CIUDAD UNIVERSITARIA",
    "_company": "EDIT",
    "_stage": "E3",
    "_folderId": null,
    "PHOTOS": null
  },
  {
    "FOLIO": "170056",
    "RESULTADO_AUDITORIA": "SIN CARPETA",
    "CALLE": "SAN JAVIER",
    "COLONIA": "PLAZAS DE  SAN BUENAVENTURA",
    "DELEGACION": "CIUDAD UNIVERSITARIA",
    "_company": "EDIT",
    "_stage": "E3",
    "_folderId": null,
    "PHOTOS": null
  },
  {
    "FOLIO": "170057",
    "RESULTADO_AUDITORIA": "SIN CARPETA",
    "CALLE": "SAN JAVIER",
    "COLONIA": "PLAZAS DE  SAN BUENAVENTURA",
    "DELEGACION": "CIUDAD UNIVERSITARIA",
    "_company": "EDIT",
    "_stage": "E3",
    "_folderId": null,
    "PHOTOS": null
  },
  {
    "FOLIO": "170058",
    "RESULTADO_AUDITORIA": "SIN CARPETA",
    "CALLE": "SAN JAVIER",
    "COLONIA": "PLAZAS DE  SAN BUENAVENTURA",
    "DELEGACION": "CIUDAD UNIVERSITARIA",
    "_company": "EDIT",
    "_stage": "E3",
    "_folderId": null,
    "PHOTOS": null
  },
  {
    "FOLIO": "170059",
    "RESULTADO_AUDITORIA": "OK",
    "CALLE": "SAN JAVIER",
    "COLONIA": "PLAZAS DE  SAN BUENAVENTURA",
    "DELEGACION": "CIUDAD UNIVERSITARIA",
    "_company": "EDIT",
    "_stage": "E3",
    "_folderId": "1A3tmmO5Uga75ehHtUTExLZgixjQxU2JU",
    "PHOTOS": {
      "INICIAL": {
        "thumbnail": "https://lh3.googleusercontent.com/drive-storage/AJQWtBPcpiDnVt_73Nor8cINOH40aZ3-HDAEMbZe9TZCRC39TM1-qknBIwksSiRBa5CkowKV_ycBUD0uaz6q1zZtAhSLGrS5fivnD869TVFNdT-nhObZ2cU=s220",
        "view": "https://drive.google.com/file/d/1zbMLaqdErBycVgLixjlL2PTtS6rjMcbr/view?usp=drivesdk"
      },
      "CAJA": {
        "thumbnail": "https://lh3.googleusercontent.com/drive-storage/AJQWtBMNx__x7jY6HDDWLErc0E87u-CmohsrHn1YlygAsVFuY1o2XeXCEkb7A39ScrBUWmVIbiz9RMf7NzGJwbpSTRUOL1k8WDuXbnql4MCRopVsCcY3Y0o=s220",
        "view": "https://drive.google.com/file/d/1dAbrm9Fd7Ih46WkFRd_fgRxFHyRj0o2v/view?usp=drivesdk"
      },
      "FINAL": {
        "thumbnail": "https://lh3.googleusercontent.com/drive-storage/AJQWtBMV5tmqdIj15QGJQr5M-zCC3nIrY2NtcSMm-9WLQlcYhYLqXdr0UH2IY_o8g4Ul8zqoAMcXJppdg-JeUAH1OCNxWYNcY31GY2PKEiPGNBOD-cKfjDM=s220",
        "view": "https://drive.google.com/file/d/1CkkL4TxeGb-_K6lAiLeCYXF7gzX-wDDe/view?usp=drivesdk"
      }
    }
  },
  {
    "FOLIO": "170060",
    "RESULTADO_AUDITORIA": "OK",
    "CALLE": "SAN JAVIER",
    "COLONIA": "PLAZAS DE  SAN BUENAVENTURA",
    "DELEGACION": "CIUDAD UNIVERSITARIA",
    "_company": "EDIT",
    "_stage": "E3",
    "_folderId": "1sY2N01bC_NvtYFZ5zybtdgWPqadFZ4LZ",
    "PHOTOS": {
      "INICIAL": {
        "thumbnail": "https://lh3.googleusercontent.com/drive-storage/AJQWtBNo51Y9LuwXol-mhadI4OiiRkoMtRT0RyO8sQqTcbqLRrv008WfuWik5wuUktkSGmxHkM6K8W71wBXwD3My-dQF5oaLf5x0wLFXNQmnLjS1rizGTik=s220",
        "view": "https://drive.google.com/file/d/1TYOvXXYGq4sl-Fn12G3WSFV1oz1nNrzg/view?usp=drivesdk"
      },
      "CAJA": {
        "thumbnail": "https://lh3.googleusercontent.com/drive-storage/AJQWtBNi9Q3YVzdbq0qrU7OudTh98wjELR-dKYvRNvAKr3lUnuXbgPEUYLNQFO6f697bJRivARKZOq2quVF9P1zsW8OcGN0qaZo4jwcE8TiyYYwF5JJ0NTg=s220",
        "view": "https://drive.google.com/file/d/1Q0XL6jK6yBP1A8_sWIDj-F2AF6tyL-gU/view?usp=drivesdk"
      },
      "FINAL": {
        "thumbnail": "https://lh3.googleusercontent.com/drive-storage/AJQWtBMUul9-hqtg6iBDoiT2nJv76MIb9v1fiTH_FnJV0azOU3_R7V31n4bzRxMPifLVHk-dBAjvbD3ExbJ39q6C0T3VIpE5eXtQ0DGuWynyXQE2XhxXWPk=s220",
        "view": "https://drive.google.com/file/d/1s1AG91tYmfzbxNkBcbQBCHM6GLGMOwko/view?usp=drivesdk"
      }
    }
  },
  {
    "FOLIO": "170061",
    "RESULTADO_AUDITORIA": "OK",
    "CALLE": "SAN JAVIER",
    "COLONIA": "PLAZAS DE  SAN BUENAVENTURA",
    "DELEGACION": "CIUDAD UNIVERSITARIA",
    "_company": "EDIT",
    "_stage": "E3",
    "_folderId": "1hzpvPmYK8_PWlLVWCKg0DEpVxjZf7lBM",
    "PHOTOS": {
      "INICIAL": {
        "thumbnail": "https://lh3.googleusercontent.com/drive-storage/AJQWtBNIutCSJ_TfoQ7jqz4O0b2gfWgWPc80bBQ1WxN4qhsamj36JR04CSd7y0UlIxG6565rs6KxfMBrtfKXEnOSZtoV_CUvDHR3GiLuWdGHoru0I5KsPnw=s220",
        "view": "https://drive.google.com/file/d/1K5_L1wmtigbPfQ7-E0Y62Ut2dBck88iM/view?usp=drivesdk"
      },
      "CAJA": {
        "thumbnail": "https://lh3.googleusercontent.com/drive-storage/AJQWtBP3hEu5_V6gAEOkQTsO_fKlVkpaFXJRnuCZrpjv8KuWeZTbz3TeqWDa1qnPmRwQWHqYbIJyd0I48OLmj4bWGNnY8oxv3G1LS0Spjbwy59FzQYzUY2w=s220",
        "view": "https://drive.google.com/file/d/1L8tauqg2YLEZmBKqThPn2mDTp_Z2oPVD/view?usp=drivesdk"
      },
      "FINAL": {
        "thumbnail": "https://lh3.googleusercontent.com/drive-storage/AJQWtBNsyqy7bhvfd2bY8rDw4rScPAMo-xVZgQErujLQnSbz8plYRafPEmtEg2A6JpOB_iTHusXBKruDfrlDl8wVz18nuB8WCTQMuPaMij8sHx0Kkg2WVMI=s220",
        "view": "https://drive.google.com/file/d/1ImdmZJ6kmQXeNgox7CsX5e7WCW6RYrQW/view?usp=drivesdk"
      }
    }
  },
  {
    "FOLIO": "170062",
    "RESULTADO_AUDITORIA": "OK",
    "CALLE": "ABRAZO DE ACATEMPAN",
    "COLONIA": "PLAZAS DE  SAN BUENAVENTURA",
    "DELEGACION": "CIUDAD UNIVERSITARIA",
    "_company": "EDIT",
    "_stage": "E3",
    "_folderId": "1slk0gbwyq8GbzPjIHL-Ww4U-wybLBDYg",
    "PHOTOS": {
      "INICIAL": {
        "thumbnail": "https://lh3.googleusercontent.com/drive-storage/AJQWtBPPOdhRflqKXi3JnwlwUEVZuBNDjDv1DCBPIey7nhVVRbg6kmP7-dAlYSc-jf1w9UNaswW99QtMXzLMWX-NMPcHQPWbimur7pb5MWT8lpFWvcpMdYc=s220",
        "view": "https://drive.google.com/file/d/1BXPGyUu3UYWb16KBOA6g4t9ek1zJ659C/view?usp=drivesdk"
      },
      "CAJA": {
        "thumbnail": "https://lh3.googleusercontent.com/drive-storage/AJQWtBN7NRG7GHqRMxqWTmmuEUzqfYgFSL154ng9PtI5i2LWB2a9i1JfxO-eNLA59pdJUk_qTW5OJu5ktfflfl1Sl8c5Rp2Vq4k0IicxNL_TvF6j6-I_54g=s220",
        "view": "https://drive.google.com/file/d/1lQ3HIwlJy8r6XDDemSz2vUXOG5FVwTSI/view?usp=drivesdk"
      },
      "FINAL": {
        "thumbnail": "https://lh3.googleusercontent.com/drive-storage/AJQWtBNRapPYrnxJs6cZ_LfXoPLronzO0JvU_1yLNhoDWgznF78Oc4PZg54Mp7cOrv4znTvaVqMeqNxgKYDwCnDnRNoSei0bxU5ofNx6_i4vTnHI-sylQMY=s220",
        "view": "https://drive.google.com/file/d/1_OlCQCbnF1FwANf0JgjKV1_TQdAQxM_N/view?usp=drivesdk"
      }
    }
  },
  {
    "FOLIO": "170063",
    "RESULTADO_AUDITORIA": "OK",
    "CALLE": "ABRAZO DE ACATEMPAN",
    "COLONIA": "PLAZAS DE  SAN BUENAVENTURA",
    "DELEGACION": "CIUDAD UNIVERSITARIA",
    "_company": "EDIT",
    "_stage": "E3",
    "_folderId": "1HlHJhFpGvwhE3Bvf-So_S1hQLTdWx1Ur",
    "PHOTOS": {
      "INICIAL": {
        "thumbnail": "https://lh3.googleusercontent.com/drive-storage/AJQWtBPAvS73od0yNh_6lvkM7FLd97xzeNN7JgABhjyY-RBkOad4RXLsmSQrXPUau3Z1KFyY8OyMQBn0t9P5f4ITtWbXAYYUzA8ccIzD4OlVGMLUjaEv5uA=s220",
        "view": "https://drive.google.com/file/d/1u7gcK9laS1e_F-9xcIXaMt0oaQKRESKL/view?usp=drivesdk"
      },
      "CAJA": {
        "thumbnail": "https://lh3.googleusercontent.com/drive-storage/AJQWtBNWD6TjFjSzbjSF3DwnVzZNXQIjebCyZxW3crgm14pCGX1QjA4ruPRR39BTI4NJnyLawZNs3AckPEdw54pZfMBPw0WyXjlKO7bR563uAVVkGIIDECY=s220",
        "view": "https://drive.google.com/file/d/1OgkUI7huV92Md4-wjQIpFYjsmdCV2gIs/view?usp=drivesdk"
      },
      "FINAL": {
        "thumbnail": "https://lh3.googleusercontent.com/drive-storage/AJQWtBNqC9ySgivsWOogBeVHL65dRolaDK_32cXEMt54CqdZZJCBYJj8Khg0qHZ7-rq6AGM_nHvAM6UBEOuBoVk03U51PW0Z3aae7_M246v9T5XlKi4B0IA=s220",
        "view": "https://drive.google.com/file/d/1iSFcrnPerlHTDT9y-jNdHI3vWtUq7ERi/view?usp=drivesdk"
      }
    }
  },
  {
    "FOLIO": "170064",
    "RESULTADO_AUDITORIA": "SIN CARPETA",
    "CALLE": "ABRAZO DE ACATEMPAN",
    "COLONIA": "PLAZAS DE  SAN BUENAVENTURA",
    "DELEGACION": "CIUDAD UNIVERSITARIA",
    "_company": "EDIT",
    "_stage": "E3",
    "_folderId": null,
    "PHOTOS": null
  },
  {
    "FOLIO": "170065",
    "RESULTADO_AUDITORIA": "SIN CARPETA",
    "CALLE": "ABRAZO DE ACATEMPAN",
    "COLONIA": "PLAZAS DE  SAN BUENAVENTURA",
    "DELEGACION": "CIUDAD UNIVERSITARIA",
    "_company": "EDIT",
    "_stage": "E3",
    "_folderId": null,
    "PHOTOS": null
  },
  {
    "FOLIO": "170066",
    "RESULTADO_AUDITORIA": "SIN CARPETA",
    "CALLE": "ABRAZO DE ACATEMPAN",
    "COLONIA": "PLAZAS DE  SAN BUENAVENTURA",
    "DELEGACION": "CIUDAD UNIVERSITARIA",
    "_company": "EDIT",
    "_stage": "E3",
    "_folderId": null,
    "PHOTOS": null
  },
  {
    "FOLIO": "170067",
    "RESULTADO_AUDITORIA": "SIN CARPETA",
    "CALLE": "ABRAZO DE ACATEMPAN",
    "COLONIA": "PLAZAS DE  SAN BUENAVENTURA",
    "DELEGACION": "CIUDAD UNIVERSITARIA",
    "_company": "EDIT",
    "_stage": "E3",
    "_folderId": null,
    "PHOTOS": null
  },
  {
    "FOLIO": "170068",
    "RESULTADO_AUDITORIA": "SIN CARPETA",
    "CALLE": "ABRAZO DE ACATEMPAN",
    "COLONIA": "PLAZAS DE  SAN BUENAVENTURA",
    "DELEGACION": "CIUDAD UNIVERSITARIA",
    "_company": "EDIT",
    "_stage": "E3",
    "_folderId": null,
    "PHOTOS": null
  },
  {
    "FOLIO": "170069",
    "RESULTADO_AUDITORIA": "OK",
    "CALLE": "ABRAZO DE ACATEMPAN",
    "COLONIA": "PLAZAS DE  SAN BUENAVENTURA",
    "DELEGACION": "CIUDAD UNIVERSITARIA",
    "_company": "EDIT",
    "_stage": "E3",
    "_folderId": "1zuAWOtrElMr0jtY5LdBOsdPFON-anlOm",
    "PHOTOS": {
      "INICIAL": {
        "thumbnail": "https://lh3.googleusercontent.com/drive-storage/AJQWtBO9M92BgRd91SdfRmYDQY1JIcdOBJmAx3-AXhN1NCJdngjoenT1RzQl41mVq4hU-2H4UeCwMv4SBW4KxWp6_2wYmcCyavRsoxZsTNTBREkpI6V4j1M=s220",
        "view": "https://drive.google.com/file/d/1DR8IXVkRxMGUUDG3iKG8N_hUorMfZkye/view?usp=drivesdk"
      },
      "CAJA": {
        "thumbnail": "https://lh3.googleusercontent.com/drive-storage/AJQWtBOJBhbQr4MB4CLzIMIaZLCTY2MftuCqYBljjburGTssG9hBBlPJr5t6wiC6H2cq2EVjM9xfkwt5MDujTMbJGubTGfyBd1AUWYZ9fMHlvnL4GpMwvzw=s220",
        "view": "https://drive.google.com/file/d/1p-MsPEMBIS4vs5ccy22uTN2o99nDDrXP/view?usp=drivesdk"
      },
      "FINAL": {
        "thumbnail": "https://lh3.googleusercontent.com/drive-storage/AJQWtBPMuGbsJ1psTMXiIQ17-tvJX-dOnEV3PKVoW1AJg9Exk-grk3eELr7wkaTVflV0h8fva97YKHIOC3Lu-NtS1-47GkYuIaa_Ll2hmCyFReP19XY7gkY=s220",
        "view": "https://drive.google.com/file/d/1TcuV7vmmPySNcjOBgQRlETEeWN8ezsUA/view?usp=drivesdk"
      }
    }
  }
]